fastapi_utilities/__init__.py
fastapi_utilities/repeat/__init__.py
fastapi_utilities/repeat/repeat_at.py
fastapi_utilities/repeat/repeat_every.py
fastapi_utilities/session/__init__.py
fastapi_utilities/session/session.py
fastapi_utilities/timer/__init__.py
fastapi_utilities/timer/middleware.py
fastapi_utilities-0.1.3.1.dist-info/LICENSE
fastapi_utilities-0.1.3.1.dist-info/METADATA
fastapi_utilities-0.1.3.1.dist-info/WHEEL
fastapi_utilities-0.1.3.1.dist-info/RECORD
